inferrd/__init__.py
inferrd/commandline.py
inferrd/deploy.py
inferrd/serve.py
inferrd/utils.py
inferrd-0.1.47.dist-info/LICENCE.txt
inferrd-0.1.47.dist-info/METADATA
inferrd-0.1.47.dist-info/WHEEL
inferrd-0.1.47.dist-info/entry_points.txt
inferrd-0.1.47.dist-info/top_level.txt
inferrd-0.1.47.dist-info/RECORD
