Metadata-Version: 2.1
Name: inferrd
Version: 0.1.47
Summary: inferrd.com
Home-page: https://inferrd.com
Author: inferrd.com
Author-email: contact@inferrd.com
License: MIT
Download-URL: https://pypi.org/project/inferrd/
Keywords: Inferrd,Hosting,TensorFlow,Deploy
Platform: UNKNOWN
License-File: LICENCE.txt
Requires-Dist: joblib
Requires-Dist: flask
Requires-Dist: dill
Requires-Dist: easysettings
Requires-Dist: numpy
Requires-Dist: tqdm
Requires-Dist: pandas
Requires-Dist: tensorflow
Requires-Dist: requests
